[
  {
    "scene": "MountainTownCaveA",
    "x": -124.69,
    "y": 24.13,
    "z": -110.25,
    "svgX": 1046.5269,
    "svgY": 562.86047,
    "label": "Exit to Prepper\u0027s Cache area"
  },
  {
    "scene": "MountainTownCaveA",
    "x": -75.83,
    "y": 23.92,
    "z": -86.75,
    "svgX": 641.92761,
    "svgY": 562.86047,
    "label": "Campfire, backpack"
  },
  {
    "scene": "MountainTownCaveA",
    "x": -74.92,
    "y": 15.99,
    "z": -40.03,
    "svgX": 507.06116,
    "svgY": 562.86047,
    "label": "Atrium"
  },
  {
    "scene": "MountainTownCaveA",
    "x": -68.55,
    "y": 18.24,
    "z": -18.9,
    "svgX": 372.19473,
    "svgY": 562.86047,
    "label": "Wolf carcass"
  },
  {
    "scene": "MountainTownCaveA",
    "x": -62.89,
    "y": 25.53,
    "z": -0.8,
    "svgX": 237.32831,
    "svgY": 562.86047,
    "label": "Exit to Spruce Falls Bridge area"
  },
  {
    "scene": "MountainTownCaveA",
    "x": -102.99,
    "y": 23.72,
    "z": -78.53,
    "svgX": 911.6604,
    "svgY": 562.86047,
    "label": "Crouch closest to Prepper\u0027s Cache Exit"
  },
  {
    "scene": "MountainTownCaveA",
    "x": -98.48,
    "y": 23.89,
    "z": -81.12,
    "svgX": 776.79401,
    "svgY": 562.86047,
    "label": "Crouch farthest from Prepper\u0027s Cache Exit"
  }
]